{
  "4265493618193057040": {
    "streams": [
      "https://live-en.aisports.cc/moviebox/bsy_016/playlist.m3u8",
      "http://play.sportsteam368.com/play/pao.php?id=38662342&id2=",
      "http://play.sportsteam368.com/play/mgxl.php?id=962279888&id2=",
      "http://play.sportsteam368.com/play/i11.html?id=10022500592&id2="
    ]
  },
  "8444834072392777936": {
    "streams": [
      "https://live-en.aisports.cc/moviebox/bsy_019/playlist.m3u8",
      "https://www.yangshipin.cn/tv/home?pid=600001818",
      "http://sports.cctv.com/H5/CCTV5/index.shtml",
      "http://tv.cctv.com/live/cctv5/"
    ]
  },
  "590556322258632912": {
    "streams": [
      "https://live-en.aisports.cc/moviebox/bsy_014/playlist.m3u8",
      "http://play.sportsteam368.com/play/pao.php?id=38665792&id2=",
      "http://play.sportsteam368.com/play/i11.html?id=10022500587&id2=",
      "http://nba.toutiaozb.com/qq/qq-kbs.html?matchliveid=1392688200"
    ]
  },
  "2391996173206831312": {
    "streams": [
      "https://live-en.aisports.cc/moviebox/bsy_011/playlist.m3u8",
      "http://play.sportsteam368.com/play/pao.php?id=38671202&id2=",
      "http://play.sportsteam368.com/play/j.php?id=22500590&id2=",
      "http://play.sportsteam368.com/play/kbs.html?id=10022500590&id2="
    ]
  },
  "7796315726051426512": {
    "streams": [
      "https://live-en.aisports.cc/moviebox/bsy_020/playlist.m3u8",
      "http://play.sportsteam368.com/play/j.php?id=22500588&id2=",
      "http://play.sportsteam368.com/play/kbs.html?id=10022500588&id2=",
      "http://play.sportsteam368.com/play/pao.php?id=38669042&id2="
    ]
  },
  "446441134182876520": {
    "streams": [
      "https://live-en.aisports.cc/moviebox/bsy_016/playlist.m3u8",
      "http://play.sportsteam368.com/play/kbs.html?id=10022500589&id2=",
      "http://play.sportsteam368.com/play/pao.php?id=38667952&id2=",
      "http://play.sportsteam368.com/play/j.php?id=22500589&id2="
    ]
  }
}