{
  "1573380809658090256": {
    "streams": [
      "https://live-en.aisports.cc/moviebox/device01/playlist.m3u8"
    ]
  },
  "7202403525191942352": {
    "streams": [
      "https://live-en.aisports.cc/moviebox/bsy_011/playlist.m3u8",
      "http://play.sportsteam368.com/play/kbs.html?id=vl&id2=",
      "http://play.sportsteam368.com/play/j.php?id=22500012&id2=",
      "http://play.sportsteam368.com/play/pao.php?id=vl&id2="
    ]
  },
  "8787670594026456336": {
    "streams": [
      "https://live-en.aisports.cc/moviebox/bsy_027/playlist.m3u8",
      "http://play.sportsteam368.com/play/kbs.html?id=10022500011&id2=",
      "http://play.sportsteam368.com/play/j.php?id=22500011&id2=",
      "http://play.sportsteam368.com/play/pao.php?id=38650852&id2="
    ]
  }
}